{
  "template": "git@github.com:costastf/python_project.git",
  "commit": "fa0da94f0bd02fed0d0672554328f2b6431b68d1",
  "checkout": null,
  "context": {
    "cookiecutter": {
      "project_type": "lib",
      "full_name": "Costas Tyfoxylos",
      "email": "ctyfoxylos@schubergphilis.com",
      "repo_name": "towerlib",
      "main_branch_name": "main",
      "project_slug": "towerlib",
      "project_short_description": "A python library to interface with ansible tower's (awx) api.",
      "git_url": "https://github.com/schubergphilis/towerlib.git",
      "pypi_repository": "https://upload.pypi.org/legacy/",
      "gitlab_runner_image": "# docker with python 3.7 and pipenv installed",
      "gitlab_runner_tags": "[docker]",
      "tags": "towerlib tower awx api ansible python",
      "development_status": "Beta",
      "compatible_versions": "3.7",
      "documentation_url": "https://towerlib.readthedocs.org/en/latest",
      "release_date": "02-01-2018",
      "year": "2018",
      "license": "MIT",
      "_extensions": [
        "jinja2_time.TimeExtension"
      ],
      "_template": "git@github.com:costastf/python_project.git"
    }
  },
  "directory": null
}
